insider/__init__.py
insider/__main__.py
insider/scraper.py
insider_scraper-1.0.3.dist-info/METADATA
insider_scraper-1.0.3.dist-info/WHEEL
insider_scraper-1.0.3.dist-info/dependency_links.txt
insider_scraper-1.0.3.dist-info/entry_points.txt
insider_scraper-1.0.3.dist-info/top_level.txt
insider_scraper-1.0.3.dist-info/RECORD
