Metadata-Version: 2.1
Name: insider-scraper
Version: 1.0.3
Summary: A simple CLI app for scraping events from insider.in
Home-page: https://github.com/MinatoNamikaze02/insider-scraper
Download-URL: 
Author: S Arjhun
Author-email: arjunsreedar@yahoo.com
License: MIT
Classifier: License :: OSI Approved :: MIT License
Classifier: Programming Language :: Python :: 3.7
Requires-Python: >=3.0.0
Requires-Dist: beautifulsoup4
Requires-Dist: click
Requires-Dist: selenium
